README.md
setup.py
craws/__init__.py
craws/errs.py
craws/loger.py
craws/request.py
craws/response.py
craws.egg-info/PKG-INFO
craws.egg-info/SOURCES.txt
craws.egg-info/dependency_links.txt
craws.egg-info/not-zip-safe
craws.egg-info/requires.txt
craws.egg-info/top_level.txt
craws/spiders/__init__.py
craws/spiders/air_spider.py
craws/utils/__init__.py
craws/utils/decors.py
craws/utils/funcs.py
craws/utils/pools.py